ygo/__init__.py
ygo/delay.py
ygo/exceptions.py
ygo/lazy.py
ygo/pool.py
ygo/utils.py
ygo-1.2.18.dist-info/licenses/LICENSE
ygo-1.2.18.dist-info/METADATA
ygo-1.2.18.dist-info/WHEEL
ygo-1.2.18.dist-info/top_level.txt
ygo-1.2.18.dist-info/RECORD
