Metadata-Version: 2.4
Name: ygo
Version: 1.2.18
Summary: 一个轻量级 Python 工具包，支持 并发执行（带进度条）、延迟调用、链式绑定参数、函数信息获取、模块/函数动态加载。
Project-URL: homepage, https://github.com/link-yundi/ygo
Project-URL: repository, https://github.com/link-yundi/ygo
Requires-Python: >=3.12
License-File: LICENSE
Requires-Dist: joblib>=1.5.0
Requires-Dist: logair>=1.0.6
Requires-Dist: psutil>=7.2.1
Requires-Dist: tqdm>=4.67.1
Dynamic: license-file
